javcrawler/__init__.py
javcrawler/config.py
javcrawler/crawler.py
javcrawler/logger.py
javcrawler/main.py
javcrawler/utils.py
javcrawler-0.1.0.dist-info/METADATA
javcrawler-0.1.0.dist-info/WHEEL
javcrawler-0.1.0.dist-info/entry_points.txt
javcrawler-0.1.0.dist-info/RECORD
