Metadata-Version: 2.4
Name: javcrawler
Version: 0.1.0
Summary: Add your description here
Requires-Python: ~=3.11
Requires-Dist: beautifulsoup4>=4.12.3
Requires-Dist: lxml>=5.3.0
Requires-Dist: pyyaml>=6.0.2
Requires-Dist: requests>=2.32.3
